{
    "root": {
        "props": {
            "title": "I'M EXPLODE WITH U"
        }
    },
    "content": [
        {
            "type": "HeroHeadline",
            "props": {
                "id": "hero-1",
                "eyebrow": "Project / 主策划",
                "title": "I'M EXPLODE WITH U",
                "subtitle": "我和你爆了 — Multiplayer Bubble Platform Fighter",
                "heroImage": "/images/penguin/CyberRestaurant.png",
                "navLink": ""
            }
        },
        {
            "type": "RichParagraph",
            "props": {
                "id": "desc-1",
                "content": "双人对战平台游戏。玩家扮演触碰尖锐物品会爆炸的泡泡人，通过吐泡泡推动移动并在场地上布设泡泡陷阱，争取让对手先爆炸获胜。核心乐趣在于攻击与走位之间的动态风险博弈，以及利用冰冻、爆炸等道具制造局势反转。我全权负责游戏的系统机制设计与所有对战关卡的独立搭建与迭代。"
            }
        },
        {
            "type": "BreakdownTriptych",
            "props": {
                "id": "triptych-1",
                "col1Title": "核心机制与策略深度",
                "col1Text": "设计泡泡击退机制，使攻击位移与走位布阵形成风险博弈；扩展爆炸/冰冻道具体系，丰富对抗策略层次。",
                "col1Img": "/images/penguin/CyberRestaurant.png",
                "col2Title": "关卡设计与迭代",
                "col2Text": "独立设计多张对战关卡，围绕节奏控制、视野遮挡与陷阱布置空间进行多轮迭代，优化对战体验与可读性。",
                "col2Img": "/images/penguin/CyberRestaurant.png",
                "col3Title": "双人对战框架",
                "col3Text": "构建本地双人对战的完整玩法闭环，确保匹配轮次流程、胜负判定与重开逻辑的稳定运行。",
                "col3Img": "/images/penguin/CyberRestaurant.png"
            }
        },
        {
            "type": "NextProjectBlock",
            "props": {
                "id": "next-1",
                "nextId": "parallax",
                "nextName": "SOMEWHERE BETWEEN PARALLAX",
                "nextBg": "/images/penguin/CyberRestaurant.png"
            }
        }
    ]
}
